{
  "id": "02-variablen-und-datentypen",
  "title": "Variablen und Datentypen",
  "description": "Variablen anlegen und überschreiben, die Grundtypen int, float, str und bool, die Funktion type() und Namensregeln — auf Deutsch erklärt.",
  "target_language": "de",
  "source_language": "de",
  "domain": "programming",
  "estimated_minutes": 13,
  "cards": [
    {
      "id": "py-variable",
      "front": "Variable",
      "back": "Ein benannter Speicherplatz, der einen Wert enthält. Mit = wird ihr ein Wert zugewiesen.",
      "notes": "Der Name einer Variablen ist frei wählbar — solange er den Namensregeln folgt.",
      "media_type": "text",
      "difficulty": 1,
      "tags": ["grundlagen", "variablen"]
    },
    {
      "id": "py-zuweisung",
      "front": "Zuweisung (=)",
      "back": "Der Operator = weist einer Variablen einen Wert zu: name = 'Anna' speichert den String 'Anna'.",
      "code_snippet": "name = 'Anna'\nprint(name)",
      "code_language": "python",
      "expected_output": "Anna",
      "hint": "Das = in Python ist kein Gleichheitszeichen, sondern ein Zuweisungspfeil.",
      "difficulty": 1,
      "tags": ["variablen", "syntax"],
      "media_type": "code"
    },
    {
      "id": "py-int",
      "front": "int (Ganzzahl)",
      "back": "Datentyp für ganze Zahlen ohne Nachkommastellen, z. B. 42 oder -7.",
      "code_snippet": "alter = 25\nprint(alter)",
      "code_language": "python",
      "expected_output": "25",
      "hint": "int steht für integer (englisch: ganze Zahl).",
      "difficulty": 1,
      "tags": ["datentypen", "zahlen"],
      "media_type": "code"
    },
    {
      "id": "py-float",
      "front": "float (Kommazahl)",
      "back": "Datentyp für Zahlen mit Nachkommastellen, z. B. 3.14 oder -0.5. Der Dezimaltrenner ist ein Punkt.",
      "code_snippet": "preis = 9.99\nprint(preis)",
      "code_language": "python",
      "expected_output": "9.99",
      "hint": "In Python schreibt man Kommazahlen mit einem Punkt, nicht einem Komma.",
      "difficulty": 1,
      "tags": ["datentypen", "zahlen"],
      "media_type": "code"
    },
    {
      "id": "py-str-typ",
      "front": "str (Zeichenkette)",
      "back": "Datentyp für Text. Strings stehen in einfachen oder doppelten Anführungszeichen.",
      "code_snippet": "begruessung = 'Hallo'\nprint(begruessung)",
      "code_language": "python",
      "expected_output": "Hallo",
      "hint": "str steht für string (englisch: Zeichenkette).",
      "difficulty": 1,
      "tags": ["datentypen", "strings"],
      "media_type": "code"
    },
    {
      "id": "py-bool",
      "front": "bool (Wahrheitswert)",
      "back": "Datentyp mit genau zwei Werten: True (wahr) oder False (falsch).",
      "code_snippet": "ist_angemeldet = True\nprint(ist_angemeldet)",
      "code_language": "python",
      "expected_output": "True",
      "hint": "True und False schreibt man immer mit großem Anfangsbuchstaben.",
      "difficulty": 2,
      "tags": ["datentypen", "bool"],
      "media_type": "code"
    },
    {
      "id": "py-type-funktion",
      "front": "type()",
      "back": "Gibt den Datentyp eines Wertes zurück, z. B. <class 'int'> oder <class 'str'>.",
      "code_snippet": "print(type(42))\nprint(type('Hallo'))",
      "code_language": "python",
      "expected_output": "<class 'int'>\n<class 'str'>",
      "hint": "type() hilft, wenn man nicht sicher ist, welchen Typ ein Wert hat.",
      "difficulty": 2,
      "tags": ["datentypen", "funktionen"],
      "media_type": "code"
    },
    {
      "id": "py-namensregeln",
      "front": "Namensregeln für Variablen",
      "back": "Variablennamen bestehen aus Buchstaben, Ziffern und _ . Sie dürfen nicht mit einer Ziffer beginnen und keine Leerzeichen enthalten.",
      "notes": "Python unterscheidet Groß- und Kleinschreibung: alter und Alter sind zwei verschiedene Variablen.",
      "media_type": "text",
      "difficulty": 2,
      "tags": ["variablen", "syntax"]
    },
    {
      "id": "py-ueberschreiben",
      "front": "Wert überschreiben",
      "back": "Man kann einer Variablen jederzeit einen neuen Wert zuweisen. Der alte Wert wird dabei ersetzt.",
      "code_snippet": "x = 10\nx = 20\nprint(x)",
      "code_language": "python",
      "expected_output": "20",
      "hint": "Python merkt sich nur den zuletzt zugewiesenen Wert.",
      "difficulty": 2,
      "tags": ["variablen"],
      "media_type": "code"
    },
    {
      "id": "py-snake-case",
      "front": "Snake Case",
      "back": "Schreibweise für mehrteilige Variablennamen in Python: Wörter werden mit Unterstrichen verbunden, alles klein geschrieben.",
      "notes": "Beispiel: mein_name, hoechste_punktzahl. Python-Stil bevorzugt snake_case gegenüber camelCase.",
      "media_type": "text",
      "difficulty": 2,
      "tags": ["variablen", "stil"]
    },
    {
      "id": "py-mehrere-typen",
      "front": "Vier Grundtypen im Überblick",
      "back": "int = ganze Zahl, float = Kommazahl, str = Text, bool = True/False.",
      "code_snippet": "print(type(5))\nprint(type(3.14))\nprint(type('Hi'))\nprint(type(False))",
      "code_language": "python",
      "expected_output": "<class 'int'>\n<class 'float'>\n<class 'str'>\n<class 'bool'>",
      "hint": "Jeder Wert in Python hat genau einen Datentyp.",
      "difficulty": 2,
      "tags": ["datentypen"],
      "media_type": "code"
    }
  ],
  "steps": [
    {
      "id": "intro-variablen",
      "type": "theory",
      "title": "Variablen und Zuweisung",
      "body": "# Variablen und Datentypen\n\nEine **Variable** ist ein benannter Speicherplatz. Mit dem **Zuweisungsoperator `=`** speichert man einen Wert unter einem Namen:\n\n```python\nname = 'Anna'\nalter = 25\n```\n\nDanach kann man den Namen überall im Code verwenden:\n\n```python\nprint(name)\nprint(alter)\n```\n\nAusgabe:\n\n```\nAnna\n25\n```\n\nMan kann einer Variablen jederzeit einen **neuen Wert zuweisen** — der alte wird dann ersetzt:\n\n```python\nx = 10\nx = 20\nprint(x)   # gibt 20 aus\n```"
    },
    {
      "id": "step-datentypen",
      "type": "theory",
      "title": "Die vier Grundtypen",
      "body": "## Die vier wichtigsten Datentypen\n\n| Typ | Beispiel | Bedeutung |\n|-----|----------|-----------|\n| `int` | `42` | ganze Zahl |\n| `float` | `3.14` | Kommazahl (Punkt als Trenner!) |\n| `str` | `'Hallo'` | Text (String) |\n| `bool` | `True` / `False` | Wahrheitswert |\n\nMit der Funktion **`type()`** kann man den Typ eines Wertes abfragen:\n\n```python\nprint(type(42))\nprint(type('Hallo'))\nprint(type(True))\n```\n\nAusgabe:\n\n```\n<class 'int'>\n<class 'str'>\n<class 'bool'>\n```"
    },
    {
      "id": "step-namensregeln",
      "type": "theory",
      "title": "Namensregeln und Snake Case",
      "body": "## Gültige Variablennamen\n\nFür Variablennamen gilt:\n\n- Nur **Buchstaben**, **Ziffern** und **Unterstrich** `_`.\n- **Kein Leerzeichen** — das würde Python verwirren.\n- Nicht mit einer **Ziffer beginnen**: `1name` ist ungültig, `name1` ist erlaubt.\n- Python unterscheidet **Groß- und Kleinschreibung**: `Alter` und `alter` sind zwei verschiedene Variablen.\n\nDer Python-Stilguide empfiehlt **Snake Case** für mehrteilige Namen:\n\n```python\nhoechste_punktzahl = 100\nmein_name = 'Lena'\n```\n\nUnzulässige Namen (verursachen einen `SyntaxError`):\n\n```python\n# 2wert = 5      → beginnt mit Ziffer\n# mein name = 5  → enthält Leerzeichen\n```"
    },
    {
      "id": "ex-cloze-zuweisung",
      "type": "exercise",
      "theory_ref": "intro-variablen",
      "title": "Zuweisung ergänzen",
      "exercise": {
        "id": "ex-cloze-zuweisung",
        "type": "cloze",
        "prompt": "Ergänze den Operator, mit dem man in Python einer Variablen einen Wert zuweist.",
        "card_ids": ["py-zuweisung"],
        "sentence": "In Python weist man einer Variablen einen Wert mit dem Operator ___ zu.",
        "blanks": [
          { "accept": ["="] }
        ],
        "cloze_mode": "type",
        "hint": "Die Zuweisung — nicht der doppelte Vergleichsoperator =="
      }
    },
    {
      "id": "ex-cloze-type",
      "type": "exercise",
      "theory_ref": "step-datentypen",
      "title": "type() kennenlernen",
      "exercise": {
        "id": "ex-cloze-type",
        "type": "cloze",
        "prompt": "Welche Funktion gibt den Datentyp eines Wertes zurück? Ergänze den Namen.",
        "card_ids": ["py-type-funktion"],
        "sentence": "Die Funktion ___(42) gibt <class 'int'> zurück.",
        "blanks": [
          { "accept": ["type"] }
        ],
        "cloze_mode": "type",
        "hint": "Englisch für 'Typ'."
      }
    },
    {
      "id": "ex-free-int",
      "type": "exercise",
      "theory_ref": "step-datentypen",
      "title": "Datentyp ganzer Zahlen",
      "exercise": {
        "id": "ex-free-int",
        "type": "free_text",
        "prompt": "Wie heißt der Python-Datentyp für ganze Zahlen wie 42 oder -7?",
        "card_ids": ["py-int"],
        "accept": ["int", "integer", "Int", "Integer"],
        "hint": "Abkürzung des englischen Worts für ganze Zahl.",
        "distractors": ["float", "str", "num", "number"],
        "direction": "target_to_source"
      }
    },
    {
      "id": "ex-free-bool",
      "type": "exercise",
      "theory_ref": "step-datentypen",
      "title": "Wahrheitswerte",
      "exercise": {
        "id": "ex-free-bool",
        "type": "free_text",
        "prompt": "Welche zwei Werte kann eine Variable vom Typ bool annehmen?",
        "card_ids": ["py-bool"],
        "accept": ["True und False", "False und True", "True oder False", "True, False"],
        "hint": "Beide Werte beginnen mit einem Großbuchstaben.",
        "distractors": ["0 und 1", "ja und nein", "wahr und falsch"],
        "direction": "target_to_source"
      }
    },
    {
      "id": "ex-tiles-variable",
      "type": "exercise",
      "theory_ref": "step-datentypen",
      "title": "Variable anlegen",
      "exercise": {
        "id": "ex-tiles-variable",
        "type": "word_tiles",
        "prompt": "Setze die Zeile zusammen, die der Variablen 'alter' den Wert 25 zuweist.",
        "card_ids": ["py-int"],
        "tiles": ["alter", "=", "25"],
        "hint": "Variablenname, dann Zuweisungsoperator, dann Wert.",
        "direction": "target_to_source"
      }
    },
    {
      "id": "ex-match-datentypen",
      "type": "exercise",
      "theory_ref": "step-datentypen",
      "title": "Datentypen zuordnen",
      "exercise": {
        "id": "ex-match-datentypen",
        "type": "matching",
        "prompt": "Ordne jeden Wert seinem Datentyp zu.",
        "card_ids": ["py-int", "py-float", "py-str-typ", "py-bool"],
        "pairs": [
          { "left": "42", "right": "int" },
          { "left": "3.14", "right": "float" },
          { "left": "'Hallo'", "right": "str" },
          { "left": "True", "right": "bool" }
        ],
        "direction": "target_to_source"
      }
    },
    {
      "id": "ex-match-regeln",
      "type": "exercise",
      "theory_ref": "step-namensregeln",
      "title": "Namensregeln prüfen",
      "exercise": {
        "id": "ex-match-regeln",
        "type": "matching",
        "prompt": "Ordne jeden Variablennamen dem richtigen Urteil zu.",
        "card_ids": ["py-namensregeln", "py-snake-case"],
        "pairs": [
          { "left": "mein_name", "right": "gültig" },
          { "left": "2wert", "right": "ungültig (beginnt mit Ziffer)" },
          { "left": "mein name", "right": "ungültig (enthält Leerzeichen)" }
        ],
        "direction": "target_to_source"
      }
    }
  ]
}
