{
  "id": "10-tupel-und-mengen",
  "title": "Tupel und Mengen (tuple & set)",
  "description": "Tupel als unveränderliche geordnete Folgen und Mengen als ungeordnete Sammlungen eindeutiger Elemente — Unterschiede zu Listen, Duplikate entfernen und Mengenoperationen.",
  "target_language": "de",
  "source_language": "de",
  "domain": "programming",
  "estimated_minutes": 14,
  "cards": [
    {
      "id": "tuple-erstellen",
      "front": "Tupel erstellen (tuple)",
      "back": "Ein Tupel speichert mehrere Werte in runden Klammern. Es ist unveränderlich — nach der Erstellung können keine Elemente hinzugefügt oder entfernt werden.",
      "code_snippet": "punkt = (3, 7)\nprint(punkt)",
      "code_language": "python",
      "expected_output": "(3, 7)",
      "hint": "Runde Klammern ( ) statt eckige [ ].",
      "difficulty": 2,
      "tags": ["tupel", "grundlagen"],
      "media_type": "code"
    },
    {
      "id": "tuple-index",
      "front": "Tupel-Element abrufen",
      "back": "Auf Tupel-Elemente greift man wie bei Listen per Index zu. Der erste Index ist 0.",
      "code_snippet": "punkt = (3, 7)\nprint(punkt[0])",
      "code_language": "python",
      "expected_output": "3",
      "hint": "Eckige Klammern für den Index, wie bei Listen.",
      "difficulty": 2,
      "tags": ["tupel", "indexing"],
      "media_type": "code"
    },
    {
      "id": "tuple-unveraenderlich",
      "front": "Unveränderlichkeit (immutable)",
      "back": "Ein Tupel kann nach der Erstellung nicht verändert werden. Der Versuch, ein Element zu ändern, führt zu einem TypeError.",
      "notes": "Das macht Tupel sicherer als Listen, wenn die Daten konstant bleiben sollen.",
      "media_type": "text",
      "difficulty": 3,
      "tags": ["tupel", "eigenschaft"]
    },
    {
      "id": "tuple-vs-liste",
      "front": "Tupel vs. Liste",
      "back": "Listen sind veränderlich (mutable) und stehen in [ ]. Tupel sind unveränderlich (immutable) und stehen in ( ). Beide sind geordnet und erlauben doppelte Werte.",
      "media_type": "text",
      "difficulty": 2,
      "tags": ["tupel", "liste", "vergleich"]
    },
    {
      "id": "set-erstellen",
      "front": "Menge erstellen (set)",
      "back": "Eine Menge speichert eindeutige Elemente ohne feste Reihenfolge. Sie wird mit geschweiften Klammern oder set() erstellt.",
      "code_snippet": "farben = {'rot', 'gruen', 'blau'}\nprint(len(farben))",
      "code_language": "python",
      "expected_output": "3",
      "hint": "Geschweifte Klammern wie bei Dictionaries, aber ohne Schlüssel-Wert-Paare.",
      "difficulty": 2,
      "tags": ["menge", "grundlagen"],
      "media_type": "code"
    },
    {
      "id": "set-duplikate",
      "front": "Duplikate entfernen mit set()",
      "back": "set() aus einer Liste erstellt eine Menge und entfernt dabei alle doppelten Werte automatisch.",
      "code_snippet": "zahlen = [1, 2, 2, 3, 3, 3]\neindeutig = set(zahlen)\nprint(len(eindeutig))",
      "code_language": "python",
      "expected_output": "3",
      "hint": "set() akzeptiert jedes iterable Objekt.",
      "difficulty": 2,
      "tags": ["menge", "duplikate"],
      "media_type": "code"
    },
    {
      "id": "set-in-test",
      "front": "Mengenzugehörigkeit prüfen",
      "back": "Mit dem in-Operator prüft man sehr effizient, ob ein Element in einer Menge enthalten ist.",
      "code_snippet": "farben = {'rot', 'gruen', 'blau'}\nprint('rot' in farben)",
      "code_language": "python",
      "expected_output": "True",
      "hint": "Derselbe in-Operator wie bei Listen und Dictionaries.",
      "difficulty": 2,
      "tags": ["menge", "operator"],
      "media_type": "code"
    },
    {
      "id": "set-vereinigung",
      "front": "Vereinigung (|) — set union",
      "back": "Der Operator | gibt eine neue Menge zurück, die alle Elemente beider Mengen enthält.",
      "code_snippet": "a = {1, 2, 3}\nb = {3, 4, 5}\nprint(len(a | b))",
      "code_language": "python",
      "expected_output": "5",
      "hint": "| steht für 'oder' — alle Elemente aus beiden Mengen, keine Doppelten.",
      "difficulty": 3,
      "tags": ["menge", "operation"],
      "media_type": "code"
    },
    {
      "id": "set-schnittmenge",
      "front": "Schnittmenge (&) — set intersection",
      "back": "Der Operator & gibt eine Menge zurück, die nur die Elemente enthält, die in beiden Mengen vorkommen.",
      "code_snippet": "a = {1, 2, 3}\nb = {2, 3, 4}\nprint(a & b == {2, 3})",
      "code_language": "python",
      "expected_output": "True",
      "hint": "& steht für 'und' — nur die gemeinsamen Elemente.",
      "difficulty": 3,
      "tags": ["menge", "operation"],
      "media_type": "code"
    },
    {
      "id": "set-ungeordnet",
      "front": "Mengen sind ungeordnet",
      "back": "Elemente in einer Menge haben keine feste Reihenfolge. Man kann nicht mit einem Index auf ein einzelnes Element zugreifen.",
      "notes": "Deshalb sind Mengenelemente nicht über einen Index abrufbar — dafür gibt es keine Garantie für die Reihenfolge.",
      "media_type": "text",
      "difficulty": 3,
      "tags": ["menge", "eigenschaft"]
    },
    {
      "id": "set-len",
      "front": "Anzahl der Mengenelemente",
      "back": "len(menge) gibt die Anzahl der eindeutigen Elemente in der Menge zurück.",
      "code_snippet": "s = {1, 1, 2, 3}\nprint(len(s))",
      "code_language": "python",
      "expected_output": "3",
      "hint": "Doppelte Werte zählen nur einmal.",
      "difficulty": 2,
      "tags": ["menge", "funktion"],
      "media_type": "code"
    }
  ],
  "steps": [
    {
      "id": "step-tupel",
      "type": "theory",
      "title": "Tupel — geordnet und unveränderlich",
      "body": "# Tupel und Mengen (tuple & set)\n\n## Tupel (tuple)\n\nEin **Tupel** ist wie eine Liste, aber **unveränderlich (immutable)**. Es steht in **runden Klammern** `()`:\n\n```python\npunkt = (3, 7)\nprint(punkt)     # (3, 7)\nprint(punkt[0])  # 3\n```\n\nNach der Erstellung können keine Elemente hinzugefügt, entfernt oder geändert werden. Der Versuch führt zu einem **TypeError**.\n\n## Tupel vs. Liste\n\n| Eigenschaft | Liste `[]` | Tupel `()` |\n|---|---|---|\n| Geordnet | ja | ja |\n| Doppelte Werte erlaubt | ja | ja |\n| Veränderlich | ja | **nein** |\n\nTupel eignen sich für Daten, die sich nicht ändern sollen — zum Beispiel Koordinaten oder feste Konfigurationen."
    },
    {
      "id": "step-mengen",
      "type": "theory",
      "title": "Mengen — eindeutig und ungeordnet",
      "body": "## Mengen (set)\n\nEine **Menge** speichert **eindeutige Elemente** ohne feste Reihenfolge. Sie steht in geschweiften Klammern `{}`:\n\n```python\nfarben = {'rot', 'gruen', 'blau'}\nprint(len(farben))  # 3\n```\n\n## Duplikate entfernen\n\n`set()` auf eine Liste angewendet entfernt alle doppelten Werte:\n\n```python\nzahlen = [1, 2, 2, 3, 3, 3]\nprint(len(set(zahlen)))  # 3\n```\n\n## Mengenoperationen\n\n```python\na = {1, 2, 3}\nb = {3, 4, 5}\n```\n\n- **Vereinigung** `|` — alle Elemente aus beiden Mengen: `a | b` → {1, 2, 3, 4, 5}\n- **Schnittmenge** `&` — nur gemeinsame Elemente: `a & b` → {3}\n\n## Wichtig: Mengen sind ungeordnet\n\nEs gibt keinen Index-Zugriff `menge[0]` — die Reihenfolge ist nicht garantiert. Für eine Mitgliedschaftsprüfung nutzt man **in**:\n\n```python\nprint('rot' in farben)  # True\n```"
    },
    {
      "id": "step-vergleich",
      "type": "theory",
      "title": "Überblick: Liste, Tupel und Menge",
      "body": "## Die drei Datenstrukturen im Vergleich\n\n| | Liste `[]` | Tupel `()` | Menge `{}` / `set()` |\n|---|---|---|---|\n| Geordnet | ja | ja | **nein** |\n| Duplikate erlaubt | ja | ja | **nein** |\n| Veränderlich | ja | **nein** | ja |\n| Index-Zugriff | ja | ja | **nein** |\n\n**Faustregeln:**\n- Daten sollen sich ändern → **Liste**\n- Daten sind fest (z. B. Koordinaten) → **Tupel**\n- Nur eindeutige Werte, Reihenfolge unwichtig → **Menge**"
    },
    {
      "id": "ex-cloze-tuple",
      "type": "exercise",
      "theory_ref": "step-tupel",
      "title": "Tupel-Klammern",
      "exercise": {
        "id": "ex-cloze-tuple",
        "type": "cloze",
        "prompt": "Ergänze die Klammern, in denen ein Tupel steht.",
        "card_ids": ["tuple-erstellen"],
        "sentence": "Ein Tupel wird in ___ Klammern geschrieben, z. B. (3, 7).",
        "blanks": [
          { "accept": ["runden", "runde", "()"] }
        ],
        "cloze_mode": "type",
        "hint": "Nicht eckig [ ] und nicht geschweifte { }."
      }
    },
    {
      "id": "ex-cloze-set-duplikate",
      "type": "exercise",
      "theory_ref": "step-mengen",
      "title": "Duplikate entfernen",
      "exercise": {
        "id": "ex-cloze-set-duplikate",
        "type": "cloze",
        "prompt": "Ergänze die Funktion, die aus einer Liste eine Menge ohne Duplikate erstellt.",
        "card_ids": ["set-duplikate"],
        "sentence": "Mit ___(meine_liste) entfernt man alle doppelten Werte.",
        "blanks": [
          { "accept": ["set"] }
        ],
        "cloze_mode": "type",
        "hint": "Der Datentyp für Mengen."
      }
    },
    {
      "id": "ex-free-unveraenderlich",
      "type": "exercise",
      "theory_ref": "step-tupel",
      "title": "Tupel-Eigenschaft",
      "exercise": {
        "id": "ex-free-unveraenderlich",
        "type": "free_text",
        "prompt": "Welche Eigenschaft unterscheidet ein Tupel von einer Liste — Tupel können nicht verändert werden?",
        "card_ids": ["tuple-unveraenderlich", "tuple-vs-liste"],
        "accept": ["unveränderlich", "immutable", "nicht veränderbar", "nicht veränderlich"],
        "hint": "Das englische Fachwort lautet 'immutable'.",
        "distractors": ["geordnet", "ungeordnet", "einzigartig"],
        "direction": "target_to_source"
      }
    },
    {
      "id": "ex-free-set-eigenschaft",
      "type": "exercise",
      "theory_ref": "step-mengen",
      "title": "Mengeneigenschaft",
      "exercise": {
        "id": "ex-free-set-eigenschaft",
        "type": "free_text",
        "prompt": "Was ist das besondere Merkmal einer Menge (set) in Bezug auf ihre Elemente?",
        "card_ids": ["set-erstellen", "set-duplikate"],
        "accept": ["eindeutige Elemente", "keine Duplikate", "nur eindeutige Werte", "jedes Element nur einmal", "keine doppelten Werte"],
        "hint": "Kein Element kann zweimal vorkommen.",
        "distractors": ["geordnete Elemente", "unveränderliche Elemente", "nummerierte Elemente"],
        "direction": "target_to_source"
      }
    },
    {
      "id": "ex-tiles-set-erstellen",
      "type": "exercise",
      "theory_ref": "step-mengen",
      "title": "Menge aus Liste erstellen",
      "exercise": {
        "id": "ex-tiles-set-erstellen",
        "type": "word_tiles",
        "prompt": "Setze die Zeile zusammen, die aus der Liste 'zahlen' eine Menge erstellt und deren Länge ausgibt.",
        "card_ids": ["set-duplikate"],
        "tiles": ["print", "(", "len", "(", "set", "(", "zahlen", ")", ")", ")"],
        "hint": "len() und set() sind verschachtelt, set() innen.",
        "direction": "target_to_source"
      }
    },
    {
      "id": "ex-match-datenstrukturen",
      "type": "exercise",
      "theory_ref": "step-tupel",
      "title": "Datenstrukturen zuordnen",
      "exercise": {
        "id": "ex-match-datenstrukturen",
        "type": "matching",
        "prompt": "Ordne jede Beschreibung der richtigen Datenstruktur zu.",
        "card_ids": ["tuple-erstellen", "tuple-unveraenderlich", "set-erstellen", "set-ungeordnet"],
        "pairs": [
          { "left": "Tupel ()", "right": "geordnet und unveränderlich" },
          { "left": "Menge {}", "right": "ungeordnet, nur eindeutige Elemente" },
          { "left": "Liste []", "right": "geordnet und veränderlich" },
          { "left": "set(liste)", "right": "entfernt Duplikate aus einer Liste" }
        ],
        "direction": "target_to_source"
      }
    },
    {
      "id": "ex-tiles-vereinigung",
      "type": "exercise",
      "theory_ref": "step-mengen",
      "title": "Mengenvereinigung",
      "exercise": {
        "id": "ex-tiles-vereinigung",
        "type": "word_tiles",
        "prompt": "Setze den Ausdruck zusammen, der die Vereinigung der Mengen a und b bildet und deren Länge ausgibt.",
        "card_ids": ["set-vereinigung"],
        "tiles": ["print", "(", "len", "(", "a", "|", "b", ")", ")"],
        "hint": "Der Vereinigungsoperator steht zwischen den beiden Mengen.",
        "direction": "target_to_source"
      }
    }
  ]
}
